{"fields": {"EmpID": {"type": "numerical", "min": 10001, "max": 10311}, "MarriedID": {"type": "numerical", "min": 0, "max": 1}, "GenderID": {"type": "numerical", "min": 0, "max": 1}, "DeptID": {"type": "numerical", "min": 1, "max": 6}, "Salary": {"type": "numerical", "min": 45046, "max": 250000}, "Termd": {"type": "numerical", "min": 0, "max": 1}, "PositionID": {"type": "numerical", "min": 1, "max": 30}, "CitizenDesc": {"type": "numerical", "min": 0, "max": 2}, "ManagerID": {"type": "numerical", "min": -1, "max": 39}, "EmpSatisfaction": {"type": "numerical", "min": 1, "max": 5}, "SpecialProjectsCount": {"type": "numerical", "min": 0, "max": 8}, "DaysLateLast30": {"type": "numerical", "min": 0, "max": 6}, "Absences": {"type": "numerical", "min": 1, "max": 20}, "BirthYear": {"type": "numerical", "min": 1951, "max": 1992}, "YearofTermination": {"type": "numerical", "min": -1, "max": 2018}, "YearofHire": {"type": "numerical", "min": 2006, "max": 2018}, "YearofPerformanceReview": {"type": "numerical", "min": 2010, "max": 2019}, "YearsinCompany": {"type": "numerical", "min": 0, "max": 9}}}